ImagingReso/__init__.py
ImagingReso/_utilities.py
ImagingReso/resonance.py
ImagingReso/reference_data/Bonded_H/H-C16H34.csv
ImagingReso/reference_data/Bonded_H/H-C2H4.csv
ImagingReso/reference_data/Bonded_H/H-C2H6.csv
ImagingReso/reference_data/Bonded_H/H-C3H8.csv
ImagingReso/reference_data/Bonded_H/H-C4H10.csv
ImagingReso/reference_data/Bonded_H/H-C4H6.csv
ImagingReso/reference_data/Bonded_H/H-CH4.csv
ImagingReso/reference_data/Bonded_H/H-H2.csv
ImagingReso/reference_data/Bonded_H/H-ZrH.csv
ImagingReso/reference_data/Bonded_H/_elements_list.csv
ImagingReso/reference_data/_data_for_unittest/Ag-107.csv
ImagingReso/reference_data/_data_for_unittest/Ag-109.csv
ImagingReso/reference_data/_data_for_unittest/Ag-110_m1.csv
ImagingReso/reference_data/_data_for_unittest/Ag-111.csv
ImagingReso/reference_data/_data_for_unittest/C-12.csv
ImagingReso/reference_data/_data_for_unittest/C-13.csv
ImagingReso/reference_data/_data_for_unittest/Co-58.csv
ImagingReso/reference_data/_data_for_unittest/Co-59.csv
ImagingReso/reference_data/_data_for_unittest/H-1.csv
ImagingReso/reference_data/_data_for_unittest/H-2.csv
ImagingReso/reference_data/_data_for_unittest/H-3.csv
ImagingReso/reference_data/_data_for_unittest/O-16.csv
ImagingReso/reference_data/_data_for_unittest/O-17.csv
ImagingReso/reference_data/_data_for_unittest/O-18.csv
ImagingReso/reference_data/_data_for_unittest/U-233.csv
ImagingReso/reference_data/_data_for_unittest/U-234.csv
ImagingReso/reference_data/_data_for_unittest/U-235.csv
ImagingReso/reference_data/_data_for_unittest/U-238.csv
ImagingReso/reference_data/_data_for_unittest/V-50.csv
ImagingReso/reference_data/_data_for_unittest/V-51.csv
ImagingReso/reference_data/_data_for_unittest/Zr-90.csv
ImagingReso/reference_data/_data_for_unittest/Zr-91.csv
ImagingReso/reference_data/_data_for_unittest/Zr-92.csv
ImagingReso/reference_data/_data_for_unittest/Zr-93.csv
ImagingReso/reference_data/_data_for_unittest/Zr-94.csv
ImagingReso-1.8.0.dist-info/LICENSE.txt
ImagingReso-1.8.0.dist-info/METADATA
ImagingReso-1.8.0.dist-info/WHEEL
ImagingReso-1.8.0.dist-info/top_level.txt
ImagingReso-1.8.0.dist-info/RECORD
