Metadata-Version: 2.1
Name: ImagingReso
Version: 1.8.0
Summary: tool for resonance neutron imaging
Home-page: https://github.com/ornlneutronimaging/ImagingReso.git
Author: Yuxuan Zhang, Jean Bilheux
Author-email: zhangy6@ornl.gov, bilheuxjm@ornl.gov
License: BSD
Keywords: neutron,resonance,imaging
Classifier: Development Status :: 3 - Alpha
Classifier: License :: OSI Approved :: BSD License
Classifier: Topic :: Scientific/Engineering :: Physics
Classifier: Intended Audience :: Developers
Classifier: Programming Language :: Python :: 3.10
Classifier: Natural Language :: English
License-File: LICENSE.txt
Requires-Dist: numpy
Requires-Dist: pandas
Requires-Dist: periodictable
Requires-Dist: scipy
Requires-Dist: matplotlib
Requires-Dist: six
Requires-Dist: plotly
